delink/__init__.py
delink/__main__.py
delink/_version.py
delink/ios_client.py
delink/ios_watchdog.py
delink-0.0.7.dist-info/AUTHORS
delink-0.0.7.dist-info/METADATA
delink-0.0.7.dist-info/WHEEL
delink-0.0.7.dist-info/entry_points.txt
delink-0.0.7.dist-info/pbr.json
delink-0.0.7.dist-info/top_level.txt
delink-0.0.7.dist-info/RECORD
